<Glasses>
	<Category>
	<Glass type="Large" gender="Male" color="Black" id="1011">
			<imgPath>http://demo.1000lookz.com/healthkart/assets/accessories/SunGlasses/IMG_4880.png</imgPath>
			<thumbPath>http://demo.1000lookz.com/healthkart/assets/accessories/SunGlasses/Thumb/IMG_4880.png
			</thumbPath>
			<price>1200.00</price>
			<name>Vincent Chase 1216 Black White Eyeglasses</name>
			<description>For the highly fashion conscious men and women of the modern day the BB6057 C1 eye gear from Blueberry is a real great product. It is a perfect blend of protection and style that anyone can look for during the hot summer days. It is a product that looks unique and different from the old fashioned models of eye accessories most people wear while going out to the sun. It is suitable with any of your attires and you can be sure of the way you are looking whenever you wear them.</description>
		</Glass>

		<Glass type="Medium" gender="Male" color="Mettalic" id="1011">
			<imgPath>http://demo.1000lookz.com/healthkart/assets/accessories/SunGlasses/IMG_4893.png</imgPath>
			<thumbPath>http://demo.1000lookz.com/healthkart/assets/accessories/SunGlasses/Thumb/IMG_4893.png
			</thumbPath>
			<price>1500.00</price>
			<name>Vincent Chase 1216 Black White Eyeglasses</name>
			<description>For the highly fashion conscious men and women of the modern day the BB6057 C1 eye gear from Blueberry is a real great product. It is a perfect blend of protection and style that anyone can look for during the hot summer days. It is a product that looks unique and different from the old fashioned models of eye accessories most people wear while going out to the sun. It is suitable with any of your attires and you can be sure of the way you are looking whenever you wear them.</description>
		</Glass>

		<Glass type="Small" gender="Female" color="Mettalic" id="1011">
			<imgPath>http://demo.1000lookz.com/healthkart/assets/accessories/SunGlasses/IMG_4907.png</imgPath>
			<thumbPath>http://demo.1000lookz.com/healthkart/assets/accessories/SunGlasses/Thumb/IMG_4907.png
			</thumbPath>
			<price>1800.00</price>
			<name>Vincent Chase 1216 Black White Eyeglasses</name>
			<description>For the highly fashion conscious men and women of the modern day the BB6057 C1 eye gear from Blueberry is a real great product. It is a perfect blend of protection and style that anyone can look for during the hot summer days. It is a product that looks unique and different from the old fashioned models of eye accessories most people wear while going out to the sun. It is suitable with any of your attires and you can be sure of the way you are looking whenever you wear them.</description>
		</Glass>

		<Glass type="Large" gender="Male" color="Black" id="1011">
			<imgPath>http://demo.1000lookz.com/healthkart/assets/accessories/SunGlasses/IMG_4923.png</imgPath>
			<thumbPath>http://demo.1000lookz.com/healthkart/assets/accessories/SunGlasses/Thumb/IMG_4923.png
			</thumbPath>
			<price>1500.00</price>
			<name>Vincent Chase 1216 Black White Eyeglasses</name>
			<description>For the highly fashion conscious men and women of the modern day the BB6057 C1 eye gear from Blueberry is a real great product. It is a perfect blend of protection and style that anyone can look for during the hot summer days. It is a product that looks unique and different from the old fashioned models of eye accessories most people wear while going out to the sun. It is suitable with any of your attires and you can be sure of the way you are looking whenever you wear them.</description>
		</Glass>

		<Glass type="Medium" gender="Male" color="Green" id="1011">
			<imgPath>http://demo.1000lookz.com/healthkart/assets/accessories/SunGlasses/IMG_4932.png</imgPath>
			<thumbPath>http://demo.1000lookz.com/healthkart/assets/accessories/SunGlasses/Thumb/IMG_4932.png
			</thumbPath>
			<price>1200.00</price>
			<name>Vincent Chase 1216 Black White Eyeglasses</name>
			<description>For the highly fashion conscious men and women of the modern day the BB6057 C1 eye gear from Blueberry is a real great product. It is a perfect blend of protection and style that anyone can look for during the hot summer days. It is a product that looks unique and different from the old fashioned models of eye accessories most people wear while going out to the sun. It is suitable with any of your attires and you can be sure of the way you are looking whenever you wear them.</description>
		</Glass>
	</Category>
</Glasses>